[ {
  "imgUrl" : "https://asforos.by/upload/resize_cache/iblock/f83/500_500_17236f3bb137eb253405d06e58cacf26c/f83ebca663e8ebf58db3193f9f21eeeb.JPG",
  "title" : "Карниз 2-рядный «Ажур» D25 Риф / Риф Антик",
  "price" : "",
  "moreDetailsUrl" : "https://asforos.by/karnizy/karniz-2-ryadnyy-azhur-d25-rif-rif-antik/",
  "category" : "flexible",
  "properties" : {
    "Цвет" : "Антик",
    "Диаметр (мм)" : "25",
    "Тип трубы" : "Рифлёная",
    "Количество рядов" : "2"
  },
  "propertiesFromDetailPage" : {
    "Цвет" : [ "src='https://asforos.by/upload/uf/592/592a69ae3e9295aa9fbc8c087824694f.jpg' alt='Антик'" ],
    "Количество рядов" : [ "2", "-" ],
    "Тип трубы" : [ "Рифлёная / Рифлёная", "-" ],
    "Длина (м)" : [ "1,6", "1,8", "2,0", "2,4", "3,0", "-" ],
    "Тип колец" : [ "Простое", "Простое с крючком", "Простое с зажимом", "Бесшумное", "Бесшумное с крючком", "Бесшумное с зажимом", "-" ]
  }
}, {
  "imgUrl" : "https://asforos.by/upload/resize_cache/iblock/f38/500_500_17236f3bb137eb253405d06e58cacf26c/f38375b506feb1a5c2aeac4b7bcaafd9.JPG",
  "title" : "Наконечник D16 «Лира»",
  "price" : "",
  "moreDetailsUrl" : "https://asforos.by/karnizy/nakonechnik-d16-lira/",
  "category" : "flexible",
  "properties" : {
    "Диаметр (мм)" : "16"
  },
  "propertiesFromDetailPage" : {
    "Цвет" : [ "src='https://asforos.by/upload/uf/592/592a69ae3e9295aa9fbc8c087824694f.jpg' alt='Антик'", "src='https://asforos.by/upload/uf/5b6/5b653c44b641d9ef83145d79cb2ebed1.jpg' alt='Сатин'" ]
  }
}, {
  "imgUrl" : "https://asforos.by/upload/resize_cache/iblock/91e/500_500_17236f3bb137eb253405d06e58cacf26c/91ed14b44f37c75f813fa00c564a161e.JPG",
  "title" : "Карниз 2-рядный «Верди» D25 Риф / Риф Антик",
  "price" : "",
  "moreDetailsUrl" : "https://asforos.by/karnizy/karniz-2-ryadnyy-verdi-d25-rif-rif-antik/",
  "category" : "flexible",
  "properties" : {
    "Цвет" : "Антик",
    "Диаметр (мм)" : "25",
    "Тип трубы" : "Рифлёная",
    "Количество рядов" : "2"
  },
  "propertiesFromDetailPage" : {
    "Цвет" : [ "src='https://asforos.by/upload/uf/592/592a69ae3e9295aa9fbc8c087824694f.jpg' alt='Антик'" ],
    "Количество рядов" : [ "2", "-" ],
    "Тип трубы" : [ "Рифлёная / Рифлёная", "-" ],
    "Длина (м)" : [ "1,6", "1,8", "2,0", "2,4", "3,0", "-" ],
    "Тип колец" : [ "Простое", "Простое с крючком", "Простое с зажимом", "Бесшумное", "Бесшумное с крючком", "Бесшумное с зажимом", "-" ]
  }
}, {
  "imgUrl" : "https://asforos.by/upload/resize_cache/iblock/4c3/500_500_17236f3bb137eb253405d06e58cacf26c/4c3e21dd954e8223c1c0cfcaca9f9996.jpg",
  "title" : "Наконечник D19 «Нордик»",
  "price" : "",
  "moreDetailsUrl" : "https://asforos.by/karnizy/nakonechnik-d19-nordik/",
  "category" : "flexible",
  "properties" : {
    "Диаметр (мм)" : "19"
  },
  "propertiesFromDetailPage" : {
    "Цвет" : [ "src='https://asforos.by/upload/uf/cbd/cbd6cdc02fadefabf875a670749a7c49.jpg' alt='Чёрный'", "src='https://asforos.by/upload/uf/e96/e966bd7eee0e43d0dc66f4a503f48ad8.jpg' alt='Белый'" ]
  }
}, {
  "imgUrl" : "https://asforos.by/upload/resize_cache/iblock/b12/500_500_17236f3bb137eb253405d06e58cacf26c/b1239e2daca4b4de9ed6301c3c80eef9.JPG",
  "title" : "Карниз 2-рядный «Метеор» D25 Риф / Риф Антик",
  "price" : "",
  "moreDetailsUrl" : "https://asforos.by/karnizy/karniz-2-ryadnyy-meteor-d25-rif-rif-antik/",
  "category" : "flexible",
  "properties" : {
    "Цвет" : "Антик",
    "Диаметр (мм)" : "25",
    "Тип трубы" : "Рифлёная",
    "Количество рядов" : "2"
  },
  "propertiesFromDetailPage" : {
    "Цвет" : [ "src='https://asforos.by/upload/uf/592/592a69ae3e9295aa9fbc8c087824694f.jpg' alt='Антик'" ],
    "Количество рядов" : [ "2", "-" ],
    "Тип трубы" : [ "Рифлёная / Рифлёная", "-" ],
    "Длина (м)" : [ "1,6", "1,8", "2,0", "2,4", "3,0", "-" ],
    "Тип колец" : [ "Простое", "Простое с крючком", "Простое с зажимом", "Бесшумное", "Бесшумное с крючком", "Бесшумное с зажимом", "-" ]
  }
}, {
  "imgUrl" : "https://asforos.by/upload/resize_cache/iblock/859/500_500_17236f3bb137eb253405d06e58cacf26c/85942e12ed5d1d984cbdeab8c790105d.jpg",
  "title" : "Наконечник D19 «Магнум»",
  "price" : "",
  "moreDetailsUrl" : "https://asforos.by/karnizy/nakonechnik-d19-magnum/",
  "category" : "flexible",
  "properties" : {
    "Диаметр (мм)" : "19"
  },
  "propertiesFromDetailPage" : {
    "Цвет" : [ "src='https://asforos.by/upload/uf/ef7/ef7289c6f79648e34ad4051fd671e8d2.jpg' alt='Хром / Белый'", "src='https://asforos.by/upload/uf/870/870ff9dcace80f7b9a8011c8445831f2.jpg' alt='Хром / Красный'", "src='https://asforos.by/upload/uf/ecf/ecf99a13121a0d9733ec2fdf1ee0e24c.jpg' alt='Хром / Чёрный'" ]
  }
}, {
  "imgUrl" : "https://asforos.by/upload/resize_cache/iblock/1af/500_500_17236f3bb137eb253405d06e58cacf26c/1af81b05b463643d8571d51ec5ab70e4.JPG",
  "title" : "Карниз 2-рядный «Тристан» D25 Гл / Гл Сатин / Чёрный",
  "price" : "",
  "moreDetailsUrl" : "https://asforos.by/karnizy/karniz-2-ryadnyy-tristan-d25-gl-gl-satin-chyernyy/",
  "category" : "flexible",
  "properties" : {
    "Цвет" : "Сатин",
    "Диаметр (мм)" : "25",
    "Тип трубы" : "Гладкая",
    "Количество рядов" : "2"
  },
  "propertiesFromDetailPage" : {
    "Цвет" : [ "src='https://asforos.by/upload/uf/4f1/4f18149888a2f87fce166173fac8ab49.jpg' alt='Сатин / Чёрный'" ],
    "Количество рядов" : [ "2", "-" ],
    "Тип трубы" : [ "Гладкая / Гладкая", "-" ],
    "Длина (м)" : [ "1,4", "1,6", "1,8", "2,0", "2,4", "3,0", "-" ],
    "Тип колец" : [ "Простое", "Простое с крючком", "Простое с зажимом", "Бесшумное", "Бесшумное с крючком", "Бесшумное с зажимом", "-" ]
  }
}, {
  "imgUrl" : "https://asforos.by/upload/resize_cache/iblock/c02/500_500_17236f3bb137eb253405d06e58cacf26c/c026e64ef65b204f29920d147731cdca.JPG",
  "title" : "Карниз 2-рядный «Вена» D25 Гл / Гл Сатин / Чёрный",
  "price" : "",
  "moreDetailsUrl" : "https://asforos.by/karnizy/karniz-2-ryadnyy-vena-d25-gl-gl-satin-chyernyy/",
  "category" : "flexible",
  "properties" : {
    "Цвет" : "Сатин",
    "Диаметр (мм)" : "25",
    "Тип трубы" : "Гладкая",
    "Количество рядов" : "2"
  },
  "propertiesFromDetailPage" : {
    "Цвет" : [ "src='https://asforos.by/upload/uf/4f1/4f18149888a2f87fce166173fac8ab49.jpg' alt='Сатин / Чёрный'" ],
    "Количество рядов" : [ "2", "-" ],
    "Тип трубы" : [ "Гладкая / Гладкая", "-" ],
    "Длина (м)" : [ "1,4", "1,6", "1,8", "2,0", "2,4", "3,0", "-" ],
    "Тип колец" : [ "Простое", "Простое с крючком", "Простое с зажимом", "Бесшумное", "Бесшумное с крючком", "Бесшумное с зажимом", "-" ]
  }
}, {
  "imgUrl" : "https://asforos.by/upload/resize_cache/iblock/9d1/500_500_17236f3bb137eb253405d06e58cacf26c/9d1cdea68bdc61b332a7c2e561cde8d0.JPG",
  "title" : "Карниз 2-рядный «Булава» D25 Риф / Риф Антик",
  "price" : "",
  "moreDetailsUrl" : "https://asforos.by/karnizy/karniz-2-ryadnyy-bulava-d25-rif-rif-antik/",
  "category" : "flexible",
  "properties" : {
    "Цвет" : "Антик",
    "Диаметр (мм)" : "25",
    "Тип трубы" : "Рифлёная",
    "Количество рядов" : "2"
  },
  "propertiesFromDetailPage" : {
    "Цвет" : [ "src='https://asforos.by/upload/uf/592/592a69ae3e9295aa9fbc8c087824694f.jpg' alt='Антик'" ],
    "Количество рядов" : [ "2", "-" ],
    "Тип трубы" : [ "Рифлёная / Рифлёная", "-" ],
    "Длина (м)" : [ "1,6", "1,8", "2,0", "2,4", "3,0", "-" ],
    "Тип колец" : [ "Простое", "Простое с крючком", "Простое с зажимом", "Бесшумное", "Бесшумное с крючком", "Бесшумное с зажимом", "-" ]
  }
}, {
  "imgUrl" : "https://asforos.by/upload/resize_cache/iblock/9c9/500_500_17236f3bb137eb253405d06e58cacf26c/9c921ea4f2e59e46a7d958caf39738c2.jpg",
  "title" : "Наконечник D19 «Париж»",
  "price" : "",
  "moreDetailsUrl" : "https://asforos.by/karnizy/nakonechnik-d19-parizh/",
  "category" : "flexible",
  "properties" : {
    "Диаметр (мм)" : "19"
  },
  "propertiesFromDetailPage" : {
    "Цвет" : [ "src='https://asforos.by/upload/uf/ef7/ef7289c6f79648e34ad4051fd671e8d2.jpg' alt='Хром / Белый'", "src='https://asforos.by/upload/uf/870/870ff9dcace80f7b9a8011c8445831f2.jpg' alt='Хром / Красный'", "src='https://asforos.by/upload/uf/ecf/ecf99a13121a0d9733ec2fdf1ee0e24c.jpg' alt='Хром / Чёрный'" ]
  }
}, {
  "imgUrl" : "https://asforos.by/upload/resize_cache/iblock/d1e/500_500_17236f3bb137eb253405d06e58cacf26c/d1eaf95dc532143e692aadd06a6927fe.JPG",
  "title" : "Карниз 2-рядный «Зевс» D25 Риф / Риф Антик",
  "price" : "",
  "moreDetailsUrl" : "https://asforos.by/karnizy/karniz-2-ryadnyy-zevs-d25-rif-rif-antik/",
  "category" : "flexible",
  "properties" : {
    "Цвет" : "Антик",
    "Диаметр (мм)" : "25",
    "Тип трубы" : "Рифлёная",
    "Количество рядов" : "2"
  },
  "propertiesFromDetailPage" : {
    "Цвет" : [ "src='https://asforos.by/upload/uf/592/592a69ae3e9295aa9fbc8c087824694f.jpg' alt='Антик'" ],
    "Количество рядов" : [ "2", "-" ],
    "Тип трубы" : [ "Рифлёная / Рифлёная", "-" ],
    "Длина (м)" : [ "1,6", "1,8", "2,0", "2,4", "3,0", "-" ],
    "Тип колец" : [ "Простое", "Простое с крючком", "Простое с зажимом", "Бесшумное", "Бесшумное с крючком", "Бесшумное с зажимом", "-" ]
  }
}, {
  "imgUrl" : "https://asforos.by/upload/resize_cache/iblock/8a0/500_500_17236f3bb137eb253405d06e58cacf26c/8a0f753b118d41535d343e176b03f8f2.JPG",
  "title" : "Карниз 2-рядный «Шар большой» D25 Риф / Риф Антик",
  "price" : "",
  "moreDetailsUrl" : "https://asforos.by/karnizy/karniz-2-ryadnyy-shar-bolshoy-d25-rif-rif-antik/",
  "category" : "flexible",
  "properties" : {
    "Цвет" : "Антик",
    "Диаметр (мм)" : "25",
    "Тип трубы" : "Рифлёная",
    "Количество рядов" : "2"
  },
  "propertiesFromDetailPage" : {
    "Цвет" : [ "src='https://asforos.by/upload/uf/592/592a69ae3e9295aa9fbc8c087824694f.jpg' alt='Антик'" ],
    "Количество рядов" : [ "2", "-" ],
    "Тип трубы" : [ "Рифлёная / Рифлёная", "-" ],
    "Длина (м)" : [ "1,6", "1,8", "2,0", "2,4", "3,0", "-" ],
    "Тип колец" : [ "Простое", "Простое с крючком", "Простое с зажимом", "Бесшумное", "Бесшумное с крючком", "Бесшумное с зажимом", "-" ]
  }
}, {
  "imgUrl" : "https://asforos.by/upload/resize_cache/iblock/fe0/500_500_17236f3bb137eb253405d06e58cacf26c/fe0c983667ec8420baa34c677de93162.jpg",
  "title" : "Наконечник D19 «Элис»",
  "price" : "",
  "moreDetailsUrl" : "https://asforos.by/karnizy/nakonechnik-d19-elis/",
  "category" : "flexible",
  "properties" : {
    "Диаметр (мм)" : "19"
  },
  "propertiesFromDetailPage" : {
    "Цвет" : [ "src='https://asforos.by/upload/uf/6a8/6a8ef800940aecfbfba9efe93ff23a52.jpg' alt='Хром'" ]
  }
}, {
  "imgUrl" : "https://asforos.by/upload/resize_cache/iblock/401/500_500_17236f3bb137eb253405d06e58cacf26c/401e4215d9e96aae3da41c8aa026882e.JPG",
  "title" : "Карниз 2-рядный «Корона» D25 Риф / Риф Антик",
  "price" : "",
  "moreDetailsUrl" : "https://asforos.by/karnizy/karniz-2-ryadnyy-korona-d25-rif-rif-antik/",
  "category" : "flexible",
  "properties" : {
    "Цвет" : "Антик",
    "Диаметр (мм)" : "25",
    "Тип трубы" : "Рифлёная",
    "Количество рядов" : "2"
  },
  "propertiesFromDetailPage" : {
    "Цвет" : [ "src='https://asforos.by/upload/uf/592/592a69ae3e9295aa9fbc8c087824694f.jpg' alt='Антик'" ],
    "Количество рядов" : [ "2", "-" ],
    "Тип трубы" : [ "Рифлёная / Рифлёная", "-" ],
    "Длина (м)" : [ "1,6", "1,8", "2,0", "2,4", "3,0", "-" ],
    "Тип колец" : [ "Простое", "Простое с крючком", "Простое с зажимом", "Бесшумное", "Бесшумное с крючком", "Бесшумное с зажимом", "-" ]
  }
}, {
  "imgUrl" : "https://asforos.by/upload/resize_cache/iblock/7c2/500_500_17236f3bb137eb253405d06e58cacf26c/7c23ff37c51c4f71b25f72fdc9c38064.jpg",
  "title" : "Наконечник D19 «Кристалл»",
  "price" : "",
  "moreDetailsUrl" : "https://asforos.by/karnizy/nakonechnik-d19-kristall/",
  "category" : "flexible",
  "properties" : {
    "Диаметр (мм)" : "19"
  },
  "propertiesFromDetailPage" : {
    "Цвет" : [ "src='https://asforos.by/upload/uf/cbd/cbd6cdc02fadefabf875a670749a7c49.jpg' alt='Чёрный'", "src='https://asforos.by/upload/uf/e96/e966bd7eee0e43d0dc66f4a503f48ad8.jpg' alt='Белый'" ]
  }
} ]