[ {
  "imgUrl" : "https://asforos.by/upload/resize_cache/iblock/b57/500_500_17236f3bb137eb253405d06e58cacf26c/b570ef843ae7c3a08ebd09fb64ab468e.JPG",
  "title" : "Карниз 2-рядный «Эмпория» D25 Гл / Гл Антик",
  "price" : "",
  "moreDetailsUrl" : "https://asforos.by/metallicheskie-karnizy/karniz-2-ryadnyy-emporiya-d25-gl-gl-antik/",
  "category" : "metallic",
  "properties" : {
    "Цвет" : "Антик",
    "Диаметр (мм)" : "25",
    "Тип трубы" : "Гладкая",
    "Количество рядов" : "2"
  },
  "propertiesFromDetailPage" : {
    "Цвет" : [ "src='https://asforos.by/upload/uf/592/592a69ae3e9295aa9fbc8c087824694f.jpg' alt='Антик'" ],
    "Количество рядов" : [ "2", "-" ],
    "Тип трубы" : [ "Гладкая / Гладкая", "-" ],
    "Длина (м)" : [ "1,4", "1,6", "1,8", "2,0", "2,4", "3,0", "-" ],
    "Тип колец" : [ "Простое", "Простое с крючком", "Простое с зажимом", "Бесшумное", "Бесшумное с крючком", "Бесшумное с зажимом", "-" ]
  }
}, {
  "imgUrl" : "https://asforos.by/upload/resize_cache/iblock/825/500_500_17236f3bb137eb253405d06e58cacf26c/8257cb33b8fdc69b553e5fc5667f6ca3.JPG",
  "title" : "Карниз 2-рядный «Тристан» D16 Кр / Кр Сатин / Красный",
  "price" : "",
  "moreDetailsUrl" : "https://asforos.by/metallicheskie-karnizy/karniz-2-ryadnyy-tristan-d16-kr-kr-satin-krasnyy/",
  "category" : "metallic",
  "properties" : {
    "Цвет" : "Сатин",
    "Диаметр (мм)" : "16",
    "Тип трубы" : "Крученая",
    "Количество рядов" : "2"
  },
  "propertiesFromDetailPage" : {
    "Цвет" : [ "src='https://asforos.by/upload/uf/6aa/6aad1c87aa3328ac1aafe8fdef31a3d4.jpg' alt='Сатин / Красный'" ],
    "Количество рядов" : [ "2", "-" ],
    "Тип трубы" : [ "Крученая / Крученая", "-" ],
    "Длина (м)" : [ "1,4", "1,6", "1,8", "2,0", "2,4", "3,0", "-" ],
    "Тип колец" : [ "Простое", "Простое с крючком", "Простое с зажимом", "Бесшумное", "Бесшумное с крючком", "Бесшумное с зажимом", "-" ]
  }
}, {
  "imgUrl" : "https://asforos.by/upload/resize_cache/iblock/933/500_500_17236f3bb137eb253405d06e58cacf26c/9335daa611f57f5041d5afde0dd3dc3c.JPG",
  "title" : "Карниз 2-рядный «Белуно» D16 Риф / Риф Антик",
  "price" : "",
  "moreDetailsUrl" : "https://asforos.by/metallicheskie-karnizy/karniz-2-ryadnyy-beluno-d16-rif-rif-antik/",
  "category" : "metallic",
  "properties" : {
    "Цвет" : "Антик",
    "Диаметр (мм)" : "16",
    "Тип трубы" : "Рифлёная",
    "Количество рядов" : "2"
  },
  "propertiesFromDetailPage" : {
    "Цвет" : [ "src='https://asforos.by/upload/uf/592/592a69ae3e9295aa9fbc8c087824694f.jpg' alt='Антик'" ],
    "Количество рядов" : [ "2", "-" ],
    "Тип трубы" : [ "Рифлёная / Рифлёная", "-" ],
    "Длина (м)" : [ "1,6", "1,8", "2,0", "2,4", "3,0", "-" ],
    "Тип колец" : [ "Простое", "Простое с крючком", "Простое с зажимом", "Бесшумное", "Бесшумное с крючком", "Бесшумное с зажимом", "-" ]
  }
}, {
  "imgUrl" : "https://asforos.by/upload/resize_cache/iblock/298/500_500_17236f3bb137eb253405d06e58cacf26c/298b1e10af2b9140b8bd94d193890ace.JPG",
  "title" : "Карниз 1-рядный «Сатурн» D25 Рифленая Сатин",
  "price" : "",
  "moreDetailsUrl" : "https://asforos.by/metallicheskie-karnizy/karniz-1-ryadnyy-saturn-d25-riflenaya-satin/",
  "category" : "metallic",
  "properties" : {
    "Цвет" : "Сатин",
    "Диаметр (мм)" : "25",
    "Тип трубы" : "Рифлёная",
    "Количество рядов" : "1"
  },
  "propertiesFromDetailPage" : {
    "Цвет" : [ "src='https://asforos.by/upload/uf/5b6/5b653c44b641d9ef83145d79cb2ebed1.jpg' alt='Сатин'" ],
    "Количество рядов" : [ "1", "-" ],
    "Тип трубы" : [ "Рифлёная", "-" ],
    "Длина (м)" : [ "1,6", "1,8", "2,0", "2,4", "3,0", "-" ],
    "Тип колец" : [ "Простое", "Простое с крючком", "Простое с зажимом", "Бесшумное", "Бесшумное с крючком", "Бесшумное с зажимом", "-" ]
  }
}, {
  "imgUrl" : "https://asforos.by/upload/resize_cache/iblock/ad0/500_500_17236f3bb137eb253405d06e58cacf26c/ad0d38d7643673ee2b544da7ee240abd.JPG",
  "title" : "Карниз 2-рядный «Милано» D16 Кр / Гл Антик",
  "price" : "",
  "moreDetailsUrl" : "https://asforos.by/metallicheskie-karnizy/karniz-2-ryadnyy-milano-d16-kr-gl-antik/",
  "category" : "metallic",
  "properties" : {
    "Цвет" : "Антик",
    "Диаметр (мм)" : "16",
    "Тип трубы" : "Крученая",
    "Количество рядов" : "2"
  },
  "propertiesFromDetailPage" : {
    "Цвет" : [ "src='https://asforos.by/upload/uf/592/592a69ae3e9295aa9fbc8c087824694f.jpg' alt='Антик'" ],
    "Количество рядов" : [ "2", "-" ],
    "Тип трубы" : [ "Крученая / Гладкая", "-" ],
    "Длина (м)" : [ "1,4", "1,6", "1,8", "2,0", "2,4", "3,0", "-" ],
    "Тип колец" : [ "Простое", "Простое с крючком", "Простое с зажимом", "Бесшумное", "Бесшумное с крючком", "Бесшумное с зажимом", "-" ]
  }
}, {
  "imgUrl" : "https://asforos.by/upload/resize_cache/iblock/93b/500_500_17236f3bb137eb253405d06e58cacf26c/93b31e8a4bdbd000aaf7dfeb41aef7d4.JPG",
  "title" : "Карниз 1-рядный «Спираль» D25 Рифленая Сатин",
  "price" : "",
  "moreDetailsUrl" : "https://asforos.by/metallicheskie-karnizy/karniz-1-ryadnyy-spiral-d25-riflenaya-satin/",
  "category" : "metallic",
  "properties" : {
    "Цвет" : "Сатин",
    "Диаметр (мм)" : "25",
    "Тип трубы" : "Рифлёная",
    "Количество рядов" : "1"
  },
  "propertiesFromDetailPage" : {
    "Цвет" : [ "src='https://asforos.by/upload/uf/5b6/5b653c44b641d9ef83145d79cb2ebed1.jpg' alt='Сатин'" ],
    "Количество рядов" : [ "1", "-" ],
    "Тип трубы" : [ "Рифлёная", "-" ],
    "Длина (м)" : [ "1,6", "1,8", "2,0", "2,4", "3,0", "-" ],
    "Тип колец" : [ "Простое", "Простое с крючком", "Простое с зажимом", "Бесшумное", "Бесшумное с крючком", "Бесшумное с зажимом", "-" ]
  }
}, {
  "imgUrl" : "https://asforos.by/upload/resize_cache/iblock/1de/500_500_17236f3bb137eb253405d06e58cacf26c/1dee736e65be7cd48c32c8be61dfd20e.JPG",
  "title" : "Карниз 2-рядный «Аванти» D25 Гл / Гл Антик",
  "price" : "",
  "moreDetailsUrl" : "https://asforos.by/metallicheskie-karnizy/karniz-2-ryadnyy-avanti-d25-gl-gl-antik/",
  "category" : "metallic",
  "properties" : {
    "Цвет" : "Антик",
    "Диаметр (мм)" : "25",
    "Тип трубы" : "Гладкая",
    "Количество рядов" : "2"
  },
  "propertiesFromDetailPage" : {
    "Цвет" : [ "src='https://asforos.by/upload/uf/592/592a69ae3e9295aa9fbc8c087824694f.jpg' alt='Антик'" ],
    "Количество рядов" : [ "2", "-" ],
    "Тип трубы" : [ "Гладкая / Гладкая", "-" ],
    "Длина (м)" : [ "1,4", "1,6", "1,8", "2,0", "2,4", "3,0", "-" ],
    "Тип колец" : [ "Простое", "Простое с крючком", "Простое с зажимом", "Бесшумное", "Бесшумное с крючком", "Бесшумное с зажимом", "-" ]
  }
}, {
  "imgUrl" : "https://asforos.by/upload/resize_cache/iblock/af1/500_500_17236f3bb137eb253405d06e58cacf26c/af1bb29ce5f6226fc51e44de9f4e1324.JPG",
  "title" : "Карниз 2-рядный «Изольда» D16 Кр / Кр Сатин / Красный",
  "price" : "",
  "moreDetailsUrl" : "https://asforos.by/metallicheskie-karnizy/karniz-2-ryadnyy-izolda-d16-kr-kr-satin-krasnyy/",
  "category" : "metallic",
  "properties" : {
    "Цвет" : "Сатин",
    "Диаметр (мм)" : "16",
    "Тип трубы" : "Крученая",
    "Количество рядов" : "2"
  },
  "propertiesFromDetailPage" : {
    "Цвет" : [ "src='https://asforos.by/upload/uf/6aa/6aad1c87aa3328ac1aafe8fdef31a3d4.jpg' alt='Сатин / Красный'" ],
    "Количество рядов" : [ "2", "-" ],
    "Тип трубы" : [ "Крученая / Крученая", "-" ],
    "Длина (м)" : [ "1,4", "1,6", "1,8", "2,0", "2,4", "3,0", "-" ],
    "Тип колец" : [ "Простое", "Простое с крючком", "Простое с зажимом", "Бесшумное", "Бесшумное с крючком", "Бесшумное с зажимом", "-" ]
  }
}, {
  "imgUrl" : "https://asforos.by/upload/resize_cache/iblock/fa2/500_500_17236f3bb137eb253405d06e58cacf26c/fa258c8353b01ed9a2530609c46cc656.JPG",
  "title" : "Карниз 2-рядный «Скос 2-х цвет.» D16 Риф / Риф Антик / Золото",
  "price" : "",
  "moreDetailsUrl" : "https://asforos.by/metallicheskie-karnizy/karniz-2-ryadnyy-skos-2-kh-tsvet-d16-rif-rif-antik-zoloto/",
  "category" : "metallic",
  "properties" : {
    "Цвет" : "Антик",
    "Диаметр (мм)" : "16",
    "Тип трубы" : "Рифлёная",
    "Количество рядов" : "2"
  },
  "propertiesFromDetailPage" : {
    "Цвет" : [ "src='https://asforos.by/upload/uf/a61/a61f9596148a05bb7ed48d04886cbe12.jpg' alt='Антик / Золото'" ],
    "Количество рядов" : [ "2", "-" ],
    "Тип трубы" : [ "Рифлёная / Рифлёная", "-" ],
    "Длина (м)" : [ "1,6", "1,8", "2,0", "2,4", "3,0", "-" ],
    "Тип колец" : [ "Простое", "Простое с крючком", "Простое с зажимом", "Бесшумное", "Бесшумное с крючком", "Бесшумное с зажимом", "-" ]
  }
}, {
  "imgUrl" : "https://asforos.by/upload/resize_cache/iblock/49c/500_500_17236f3bb137eb253405d06e58cacf26c/49c0797d2c02bec5fe13402a319f8cda.JPG",
  "title" : "Карниз 1-рядный «Мираж» D25 Рифленая Сатин",
  "price" : "",
  "moreDetailsUrl" : "https://asforos.by/metallicheskie-karnizy/karniz-1-ryadnyy-mirazh-d25-riflenaya-satin/",
  "category" : "metallic",
  "properties" : {
    "Цвет" : "Сатин",
    "Диаметр (мм)" : "25",
    "Тип трубы" : "Рифлёная",
    "Количество рядов" : "1"
  },
  "propertiesFromDetailPage" : {
    "Цвет" : [ "src='https://asforos.by/upload/uf/5b6/5b653c44b641d9ef83145d79cb2ebed1.jpg' alt='Сатин'" ],
    "Количество рядов" : [ "1", "-" ],
    "Тип трубы" : [ "Рифлёная", "-" ],
    "Длина (м)" : [ "1,6", "1,8", "2,0", "2,4", "3,0", "-" ],
    "Тип колец" : [ "Простое", "Простое с крючком", "Простое с зажимом", "Бесшумное", "Бесшумное с крючком", "Бесшумное с зажимом", "-" ]
  }
}, {
  "imgUrl" : "https://asforos.by/upload/resize_cache/iblock/59e/500_500_17236f3bb137eb253405d06e58cacf26c/59e5b60516e1c9322396eae78f1f1c25.JPG",
  "title" : "Карниз 2-рядный «Магнолия» D16 Кр / Гл Антик",
  "price" : "",
  "moreDetailsUrl" : "https://asforos.by/metallicheskie-karnizy/karniz-2-ryadnyy-magnoliya-d16-kr-gl-antik/",
  "category" : "metallic",
  "properties" : {
    "Цвет" : "Антик",
    "Диаметр (мм)" : "16",
    "Тип трубы" : "Крученая",
    "Количество рядов" : "2"
  },
  "propertiesFromDetailPage" : {
    "Цвет" : [ "src='https://asforos.by/upload/uf/592/592a69ae3e9295aa9fbc8c087824694f.jpg' alt='Антик'" ],
    "Количество рядов" : [ "2", "-" ],
    "Тип трубы" : [ "Крученая / Гладкая", "-" ],
    "Длина (м)" : [ "1,4", "1,6", "1,8", "2,0", "2,4", "3,0", "-" ],
    "Тип колец" : [ "Простое", "Простое с крючком", "Простое с зажимом", "Бесшумное", "Бесшумное с крючком", "Бесшумное с зажимом", "-" ]
  }
}, {
  "imgUrl" : "https://asforos.by/upload/resize_cache/iblock/bc1/500_500_17236f3bb137eb253405d06e58cacf26c/bc178b50966c5a2f13ba51eaf4ef065a.JPG",
  "title" : "Карниз 2-рядный «Буэнос» D25 Гл / Гл Антик",
  "price" : "",
  "moreDetailsUrl" : "https://asforos.by/metallicheskie-karnizy/karniz-2-ryadnyy-buenos-d25-gl-gl-antik/",
  "category" : "metallic",
  "properties" : {
    "Цвет" : "Антик",
    "Диаметр (мм)" : "25",
    "Тип трубы" : "Гладкая",
    "Количество рядов" : "2"
  },
  "propertiesFromDetailPage" : {
    "Цвет" : [ "src='https://asforos.by/upload/uf/592/592a69ae3e9295aa9fbc8c087824694f.jpg' alt='Антик'" ],
    "Количество рядов" : [ "2", "-" ],
    "Тип трубы" : [ "Гладкая / Гладкая", "-" ],
    "Длина (м)" : [ "1,4", "1,6", "1,8", "2,0", "2,4", "3,0", "-" ],
    "Тип колец" : [ "Простое", "Простое с крючком", "Простое с зажимом", "Бесшумное", "Бесшумное с крючком", "Бесшумное с зажимом", "-" ]
  }
}, {
  "imgUrl" : "https://asforos.by/upload/resize_cache/iblock/d7c/500_500_17236f3bb137eb253405d06e58cacf26c/d7c02ae189d98abff8d6a04ccac026e5.JPG",
  "title" : "Карниз 2-рядный «Вега» D16 Риф / Риф Антик / Золото",
  "price" : "",
  "moreDetailsUrl" : "https://asforos.by/metallicheskie-karnizy/karniz-2-ryadnyy-vega-d16-rif-rif-antik-zoloto/",
  "category" : "metallic",
  "properties" : {
    "Цвет" : "Антик",
    "Диаметр (мм)" : "16",
    "Тип трубы" : "Рифлёная",
    "Количество рядов" : "2"
  },
  "propertiesFromDetailPage" : {
    "Цвет" : [ "src='https://asforos.by/upload/uf/a61/a61f9596148a05bb7ed48d04886cbe12.jpg' alt='Антик / Золото'" ],
    "Количество рядов" : [ "2", "-" ],
    "Тип трубы" : [ "Рифлёная / Рифлёная", "-" ],
    "Длина (м)" : [ "1,6", "1,8", "2,0", "2,4", "3,0", "-" ],
    "Тип колец" : [ "Простое", "Простое с крючком", "Простое с зажимом", "Бесшумное", "Бесшумное с крючком", "Бесшумное с зажимом", "-" ]
  }
}, {
  "imgUrl" : "https://asforos.by/upload/resize_cache/iblock/43b/500_500_17236f3bb137eb253405d06e58cacf26c/43b06d398831d40b5f8043fd7a0f73ec.JPG",
  "title" : "Карниз 2-рядный «Заглушка плоская» D16 Кр / Гл Антик",
  "price" : "",
  "moreDetailsUrl" : "https://asforos.by/metallicheskie-karnizy/karniz-2-ryadnyy-zaglushka-ploskaya-d16-kr-gl-antik/",
  "category" : "metallic",
  "properties" : {
    "Цвет" : "Антик",
    "Диаметр (мм)" : "16",
    "Тип трубы" : "Крученая",
    "Количество рядов" : "2"
  },
  "propertiesFromDetailPage" : {
    "Цвет" : [ "src='https://asforos.by/upload/uf/592/592a69ae3e9295aa9fbc8c087824694f.jpg' alt='Антик'" ],
    "Количество рядов" : [ "2", "-" ],
    "Тип трубы" : [ "Крученая / Гладкая", "-" ],
    "Длина (м)" : [ "1,4", "1,6", "1,8", "2,0", "2,4", "3,0", "-" ],
    "Тип колец" : [ "Простое", "Простое с крючком", "Простое с зажимом", "Бесшумное", "Бесшумное с крючком", "Бесшумное с зажимом", "-" ]
  }
}, {
  "imgUrl" : "https://asforos.by/upload/resize_cache/iblock/143/500_500_17236f3bb137eb253405d06e58cacf26c/143953dc89647a8b2c7dd45352370675.JPG",
  "title" : "Карниз 1-рядный «Лист розы» D16 Рифленая Антик",
  "price" : "",
  "moreDetailsUrl" : "https://asforos.by/metallicheskie-karnizy/karniz-1-ryadnyy-list-rozy-d16-riflenaya-antik/",
  "category" : "metallic",
  "properties" : {
    "Цвет" : "Антик",
    "Диаметр (мм)" : "16",
    "Тип трубы" : "Рифлёная",
    "Количество рядов" : "1"
  },
  "propertiesFromDetailPage" : {
    "Цвет" : [ "src='https://asforos.by/upload/uf/592/592a69ae3e9295aa9fbc8c087824694f.jpg' alt='Антик'" ],
    "Количество рядов" : [ "1", "-" ],
    "Тип трубы" : [ "Рифлёная", "-" ],
    "Длина (м)" : [ "1,6", "1,8", "2,0", "2,4", "3,0", "-" ],
    "Тип колец" : [ "Простое", "Простое с крючком", "Простое с зажимом", "Бесшумное", "Бесшумное с крючком", "Бесшумное с зажимом", "-" ]
  }
} ]